plone/__init__.py
plone/formwidget/__init__.py
plone/formwidget/hcaptcha/__init__.py
plone/formwidget/hcaptcha/configure.zcml
plone/formwidget/hcaptcha/controlpanel.py
plone/formwidget/hcaptcha/i18n.py
plone/formwidget/hcaptcha/interfaces.py
plone/formwidget/hcaptcha/meta.zcml
plone/formwidget/hcaptcha/nohcaptcha.py
plone/formwidget/hcaptcha/supermodel.py
plone/formwidget/hcaptcha/testing.py
plone/formwidget/hcaptcha/upgrades.py
plone/formwidget/hcaptcha/validator.py
plone/formwidget/hcaptcha/view.py
plone/formwidget/hcaptcha/widget.pt
plone/formwidget/hcaptcha/widget.py
plone/formwidget/hcaptcha/widget_display.pt
plone/formwidget/hcaptcha/demo/__init__.py
plone/formwidget/hcaptcha/demo/configure.zcml
plone/formwidget/hcaptcha/demo/form.py
plone/formwidget/hcaptcha/locales/__init__.py
plone/formwidget/hcaptcha/locales/__main__.py
plone/formwidget/hcaptcha/locales/plone.formwidget.hcaptcha.pot
plone/formwidget/hcaptcha/locales/de/LC_MESSAGES/plone.formwidget.hcaptcha.mo
plone/formwidget/hcaptcha/locales/de/LC_MESSAGES/plone.formwidget.hcaptcha.po
plone/formwidget/hcaptcha/locales/es/LC_MESSAGES/plone.formwidget.hcaptcha.mo
plone/formwidget/hcaptcha/locales/es/LC_MESSAGES/plone.formwidget.hcaptcha.po
plone/formwidget/hcaptcha/locales/eu/LC_MESSAGES/plone.formwidget.hcaptcha.mo
plone/formwidget/hcaptcha/locales/eu/LC_MESSAGES/plone.formwidget.hcaptcha.po
plone/formwidget/hcaptcha/locales/nl/LC_MESSAGES/plone.formwidget.hcaptcha.mo
plone/formwidget/hcaptcha/locales/nl/LC_MESSAGES/plone.formwidget.hcaptcha.po
plone/formwidget/hcaptcha/locales/pt_BR/LC_MESSAGES/plone.formwidget.hcaptcha.mo
plone/formwidget/hcaptcha/locales/pt_BR/LC_MESSAGES/plone.formwidget.hcaptcha.po
plone/formwidget/hcaptcha/profiles/default/browserlayer.xml
plone/formwidget/hcaptcha/profiles/default/controlpanel.xml
plone/formwidget/hcaptcha/profiles/default/metadata.xml
plone/formwidget/hcaptcha/profiles/default/registry.xml
plone/formwidget/hcaptcha/profiles/uninstall/browserlayer.xml
plone_formwidget_hcaptcha-2.0.0.dist-info/METADATA
plone_formwidget_hcaptcha-2.0.0.dist-info/WHEEL
plone_formwidget_hcaptcha-2.0.0.dist-info/entry_points.txt
plone_formwidget_hcaptcha-2.0.0.dist-info/licenses/LICENSE.GPL
plone_formwidget_hcaptcha-2.0.0.dist-info/licenses/LICENSE.md
plone_formwidget_hcaptcha-2.0.0.dist-info/RECORD
